Metadata-Version: 2.1
Name: package-dio-test01
Version: 0.0.1
Summary: DIO BootCamp UnimedBH
Home-page: https://github.com/fabiomirandamonte/-dio-desafio-image-processing-package.git
Author: fabiomirandamonte
Author-email: fabiomirandamonte@gmail.com
Requires-Python: >=3.8
Requires-Dist: matplotlib
Requires-Dist: numpy
Requires-Dist: scikit-image (>=0.16.1)
